setup.py
lib/pyxval/__init__.py
lib/pyxval/_basescorer.py
lib/pyxval/_basestats.py
lib/pyxval/_continuousperfstats.py
lib/pyxval/_crossvalidator.py
lib/pyxval/_discreteperfstats.py
lib/pyxval/_gridsearcher.py
lib/pyxval/_logging.py
lib/pyxval/_nestedcrossvalidator.py
lib/pyxval/_normalvalue.py
lib/pyxval/_proxyclassifierfactory.py
lib/pyxval/_selectinggridsearcher.py
lib/pyxval/_selectingnestedcrossvalidator.py
lib/pyxval/_validationresult.py
lib/pyxval/_validator.py
lib/pyxval/_fakemp/__init__.py
lib/pyxval/_tests/__init__.py
lib/pyxval/_tests/_optimist.py
lib/pyxval/_tests/_testcrossvalidator.py
lib/pyxval/_tests/_testgridsearcher.py
lib/pyxval/_tests/_testnestedcrossvalidator.py
lib/pyxval/_tests/_testpickling.py
pyxval.egg-info/PKG-INFO
pyxval.egg-info/SOURCES.txt
pyxval.egg-info/dependency_links.txt
pyxval.egg-info/top_level.txt