Metadata-Version: 1.1
Name: pyxval
Version: 0.9.3
Summary: Machine learning cross-validation framework
Home-page: http://github.com/nlhepler/pyxval
Author: N Lance Hepler
Author-email: nlhepler@gmail.com
License: GNU GPL version 3
Platform: UNKNOWN
Requires: six
